README.md
setup.py
langswi/__init__.py
langswi/main.py
langswi/mapping.py
langswi.egg-info/PKG-INFO
langswi.egg-info/SOURCES.txt
langswi.egg-info/dependency_links.txt
langswi.egg-info/entry_points.txt
langswi.egg-info/top_level.txt