Metadata-Version: 1.1
Name: langswi
Version: 0.1.1
Summary: Cyrillic-latin and reverse text transformation
Home-page: https://github.com/sonerayberk/langswi/
Author: sonerayberk
Author-email: soner.ayberk@gmail.com
License: BSD
Keywords: language switcher text transformation translation
Platform: UNKNOWN
Classifier: Intended Audience :: Developers
Classifier: License :: OSI Approved :: BSD License
Classifier: Operating System :: OS Independent
Classifier: Programming Language :: Python
Classifier: Programming Language :: Python :: 3
